stra/__init__.py
stra-0.0.1.dist-info/DESCRIPTION.rst
stra-0.0.1.dist-info/METADATA
stra-0.0.1.dist-info/RECORD
stra-0.0.1.dist-info/WHEEL
stra-0.0.1.dist-info/entry_points.txt
stra-0.0.1.dist-info/metadata.json
stra-0.0.1.dist-info/top_level.txt
