Metadata-Version: 2.0
Name: stra
Version: 0.0.1
Summary: Annotates the output of running a command with the name of the corresponding stream
Home-page: https://github.com/toastedcornflakes/STReam-Annotate
Author: toastedcornflakes
Author-email: toastedcornflakes@gmail.com
License: BSD
Platform: UNKNOWN
